LearningRust/README.md
LearningRust/__init__.py
LearningRust/__main__.py
LearningRust/file.epub
LearningRust/index.html
LearningRust/css/__init__.py
LearningRust/css/annotations.css
LearningRust/css/main.css
LearningRust/css/normalize.css
LearningRust/css/popup.css
LearningRust/font/__init__.py
LearningRust/font/fontello.eot
LearningRust/font/fontello.svg
LearningRust/font/fontello.ttf
LearningRust/font/fontello.woff
LearningRust/img/__init__.py
LearningRust/img/annotator-glyph-sprite.png
LearningRust/img/annotator-icon-sprite.png
LearningRust/img/apple-touch-icon.png
LearningRust/img/cancelfullscreen.png
LearningRust/img/close.png
LearningRust/img/fullscreen.png
LearningRust/img/loader.gif
LearningRust/img/menu-icon.png
LearningRust/img/save.png
LearningRust/img/saved.png
LearningRust/img/settings-s.png
LearningRust/img/settings.png
LearningRust/img/star.png
LearningRust/js/__init__.py
LearningRust/js/epub.js
LearningRust/js/epub.min.js
LearningRust/js/epub.min.map
LearningRust/js/hooks.min.js
LearningRust/js/hooks.min.map
LearningRust/js/reader.js
LearningRust/js/reader.js.map
LearningRust/js/reader.min.js
LearningRust/js/reader.min.map
LearningRust/js/hooks/__init__.py
LearningRust/js/hooks/extensions/__init__.py
LearningRust/js/hooks/extensions/highlight.js
LearningRust/js/libs/__init__.py
LearningRust/js/libs/jquery.min.js
LearningRust/js/libs/localforage.min.js
LearningRust/js/libs/screenfull.js
LearningRust/js/libs/screenfull.min.js
LearningRust/js/libs/zip.min.js
LearningRust/js/plugins/__init__.py
LearningRust/js/plugins/hypothesis.js
LearningRust/js/plugins/search.js
learning_rust-2024.3.3.0.dist-info/METADATA
learning_rust-2024.3.3.0.dist-info/WHEEL
learning_rust-2024.3.3.0.dist-info/entry_points.txt
learning_rust-2024.3.3.0.dist-info/top_level.txt
learning_rust-2024.3.3.0.dist-info/RECORD
